README.md
setup.py
pumpkin_supmcu/linux/__init__.py
pumpkin_supmcu/linux/linux.py
pumpkin_supmcu_smbus.egg-info/PKG-INFO
pumpkin_supmcu_smbus.egg-info/SOURCES.txt
pumpkin_supmcu_smbus.egg-info/dependency_links.txt
pumpkin_supmcu_smbus.egg-info/not-zip-safe
pumpkin_supmcu_smbus.egg-info/requires.txt
pumpkin_supmcu_smbus.egg-info/top_level.txt